{"id":"node_modules/@therms/models/index.js","dependencies":[{"name":"/Users/coryrobinson/projects/js-data-client/node_modules/@therms/models/package.json","includedInParent":true,"mtime":1539897253717},{"name":"/Users/coryrobinson/projects/js-data-client/package.json","includedInParent":true,"mtime":1538419449751},{"name":"/Users/coryrobinson/projects/js-data-client/node_modules/@therms/models/.babelrc","includedInParent":true,"mtime":1538423057578},{"name":"./mappers","loc":{"line":1,"column":28},"parent":"/Users/coryrobinson/projects/js-data-client/node_modules/@therms/models/index.js","resolved":"/Users/coryrobinson/projects/js-data-client/node_modules/@therms/models/mappers/index.js"}],"generated":{"js":"const Definitions = require('./mappers');\n\nmodule.exports = {\n  Definitions\n};\n","map":{"mappings":[{"source":"node_modules/@therms/models/index.js","original":{"line":1,"column":0},"generated":{"line":1,"column":0}},{"source":"node_modules/@therms/models/index.js","original":{"line":2,"column":0},"generated":{"line":2,"column":0}},{"source":"node_modules/@therms/models/index.js","original":{"line":3,"column":0},"generated":{"line":3,"column":0}},{"source":"node_modules/@therms/models/index.js","original":{"line":4,"column":0},"generated":{"line":4,"column":0}},{"source":"node_modules/@therms/models/index.js","original":{"line":5,"column":0},"generated":{"line":5,"column":0}},{"source":"node_modules/@therms/models/index.js","original":{"line":6,"column":0},"generated":{"line":6,"column":0}}],"sources":{"node_modules/@therms/models/index.js":"const Definitions = require('./mappers');\n\nmodule.exports = {\n  Definitions\n};\n"},"lineCount":6}},"hash":"4aaf57a2e4c19b16c168723e4217c617","cacheData":{"env":{}}}